dfgcompare/__init__.py
dfgcompare/dataset/__init__.py
dfgcompare/dataset/hospital/__init__.py
dfgcompare/dataset/hospital/sampleData.py
dfgcompare/dfg/__init__.py
dfgcompare/dfg/compute.py
dfgcompare/dfg/visualize.py
dfgcompare/dfg/stochastic/__init__.py
dfgcompare/dfg/stochastic/compute.py
dfgcompare/dfg/stochastic/visualize.py
dfgcompare-0.0.7.dist-info/METADATA
dfgcompare-0.0.7.dist-info/WHEEL
dfgcompare-0.0.7.dist-info/top_level.txt
dfgcompare-0.0.7.dist-info/RECORD
