Metadata-Version: 2.1
Name: dfgcompare
Version: 0.0.7
Summary: Python dfgcompare Package
Home-page: UNKNOWN
Author: Amin Jalali
Author-email: aminjalali@yahoo.com
License: MIT
Platform: UNKNOWN
Requires-Dist: pandas
Requires-Dist: graphviz
